{
  "Name": "Custom_Token",
  "Transform": {
    "posX": 66.38371,
    "posY": 1.35663915,
    "posZ": -13.5917244,
    "rotX": 0.004445269,
    "rotY": 0.000283578,
    "rotZ": 0.000150230961,
    "scaleX": 0.367304444,
    "scaleY": 1.0,
    "scaleZ": 0.367304444
  },
  "Nickname": "Element",
  "Description": "Use these for when a power/event gifts you an element or when you reveal an element on your presence tracks",
  "GMNotes": "",
  "ColorDiffuse": {
    "r": 1.0,
    "g": 1.0,
    "b": 1.0
  },
  "Locked": false,
  "Grid": false,
  "Snap": true,
  "IgnoreFoW": false,
  "MeasureMovement": false,
  "DragSelectable": true,
  "Autoraise": true,
  "Sticky": true,
  "Tooltip": true,
  "GridProjection": false,
  "HideWhenFaceDown": false,
  "Hands": false,
  "CustomImage": {
    "ImageURL": "http://cloud-3.steamusercontent.com/ugc/930436061159432741/03708EE546C237D5C21B7CA17BDFCE48A6DD904C/",
    "ImageSecondaryURL": "",
    "ImageScalar": 1.0,
    "WidthScale": 0.0,
    "CustomToken": {
      "Thickness": 0.1,
      "MergeDistancePixels": 15.0,
      "StandUp": false,
      "Stackable": false
    }
  }
}
