{
  "Name": "BlockSquare",
  "Transform": {
    "posX": 109.33,
    "posY": 0.85,
    "posZ": 42.86,
    "rotX": 0.0,
    "rotY": 180.0,
    "rotZ": 0.0,
    "scaleX": 3.4494,
    "scaleY": 0.1078,
    "scaleZ": 4.7429
  },
  "Nickname": "Blight Card Editor",
  "Description": "Place a card here to spawn buttons.\r\n\r\nSet blight to 1+.\r\n\r\nSet immediate to yes if the card only has immediate effects.\r\n\r\nSet healthy to yes if the card is still healthy on blighted side.\r\n\r\nEvery time you press a button, the card is updated.\r\n\r\nWhen finished, remember to save your object/game!",
  "GMNotes": "",
  "AltLookAngle": {
    "x": 0.0,
    "y": 0.0,
    "z": 0.0
  },
  "ColorDiffuse": {
    "r": 1.0,
    "g": 1.0,
    "b": 1.0,
    "a": 0.0824
  },
  "LayoutGroupSortIndex": 0,
  "Value": 0,
  "Locked": false,
  "Grid": true,
  "Snap": true,
  "IgnoreFoW": false,
  "MeasureMovement": false,
  "DragSelectable": true,
  "Autoraise": true,
  "Sticky": true,
  "Tooltip": true,
  "GridProjection": false,
  "HideWhenFaceDown": false,
  "Hands": false,
  "AttachedSnapPoints": [
    {
      "Position": {
        "x": 0.0,
        "y": 0.5,
        "z": 0.0
      },
      "Rotation": {
        "x": 0.0,
        "y": 0.0,
        "z": 0.0
      }
    }
  ]
}
