{
  "Name": "DeckCustom",
  "Transform": {
    "posX": -50.099998474121094,
    "posY": 0.9329411387443542,
    "posZ": 56.29999923706055,
    "rotX": -6.06331340691213e-08,
    "rotY": 180.0,
    "rotZ": 180.0,
    "scaleX": 1.5299999713897705,
    "scaleY": 1.0,
    "scaleZ": 1.5299999713897705
  },
  "Nickname": "Fear",
  "Description": "Spirit Island",
  "GMNotes": "",
  "AltLookAngle": {
    "x": 0.0,
    "y": 0.0,
    "z": 0.0
  },
  "ColorDiffuse": {
    "r": 0.7131999731063843,
    "g": 0.7131999731063843,
    "b": 0.7131999731063843
  },
  "LayoutGroupSortIndex": 0,
  "Value": 0,
  "Locked": false,
  "Grid": false,
  "Snap": true,
  "IgnoreFoW": false,
  "MeasureMovement": false,
  "DragSelectable": true,
  "Autoraise": true,
  "Sticky": true,
  "Tooltip": true,
  "GridProjection": false,
  "HideWhenFaceDown": true,
  "Hands": false,
  "SidewaysCard": false,
  "DeckIDs": [
    111500,
    111600,
    111700,
    111800,
    111900,
    112000,
    112100,
    112200,
    112300,
    112400,
    112500,
    112600,
    112700,
    112800,
    112900
  ],
  "CustomDeck": {
    "1115": {
      "FaceURL": "https://steamusercontent-a.akamaihd.net/ugc/2050875404517267974/6C4D57E7F03D4D397D7DA6B14341AA707E5FB18C/",
      "BackURL": "https://steamusercontent-a.akamaihd.net/ugc/2050875404517258684/87EDE083E71BACAF74032674A28DCBE65DAFB171/",
      "NumWidth": 1,
      "NumHeight": 1,
      "BackIsHidden": false,
      "UniqueBack": false,
      "Type": 0
    },
    "1116": {
      "FaceURL": "https://steamusercontent-a.akamaihd.net/ugc/2050875404517266533/4490A748FBEB407E205DBCF9E3942B6F4E5CFF10/",
      "BackURL": "https://steamusercontent-a.akamaihd.net/ugc/2050875404517258684/87EDE083E71BACAF74032674A28DCBE65DAFB171/",
      "NumWidth": 1,
      "NumHeight": 1,
      "BackIsHidden": false,
      "UniqueBack": false,
      "Type": 0
    },
    "1117": {
      "FaceURL": "https://steamusercontent-a.akamaihd.net/ugc/2050875404517268147/8FB9EA0286ECDD2072458CFAD529D27AB646816C/",
      "BackURL": "https://steamusercontent-a.akamaihd.net/ugc/2050875404517258684/87EDE083E71BACAF74032674A28DCBE65DAFB171/",
      "NumWidth": 1,
      "NumHeight": 1,
      "BackIsHidden": false,
      "UniqueBack": false,
      "Type": 0
    },
    "1118": {
      "FaceURL": "https://steamusercontent-a.akamaihd.net/ugc/2050875404517265569/F821F9DA8E233A426432EBF0EE96CACBB6FBB978/",
      "BackURL": "https://steamusercontent-a.akamaihd.net/ugc/2050875404517258684/87EDE083E71BACAF74032674A28DCBE65DAFB171/",
      "NumWidth": 1,
      "NumHeight": 1,
      "BackIsHidden": false,
      "UniqueBack": false,
      "Type": 0
    },
    "1119": {
      "FaceURL": "https://steamusercontent-a.akamaihd.net/ugc/2050875404517266938/E5C3D8A98960BF09C36A8E59E5C1D7C0AEFA11C2/",
      "BackURL": "https://steamusercontent-a.akamaihd.net/ugc/2050875404517258684/87EDE083E71BACAF74032674A28DCBE65DAFB171/",
      "NumWidth": 1,
      "NumHeight": 1,
      "BackIsHidden": false,
      "UniqueBack": false,
      "Type": 0
    },
    "1120": {
      "FaceURL": "https://steamusercontent-a.akamaihd.net/ugc/2050875404517267402/89E8A4B02EDF4CB0FA57DD08EA12838D02B733DA/",
      "BackURL": "https://steamusercontent-a.akamaihd.net/ugc/2050875404517258684/87EDE083E71BACAF74032674A28DCBE65DAFB171/",
      "NumWidth": 1,
      "NumHeight": 1,
      "BackIsHidden": false,
      "UniqueBack": false,
      "Type": 0
    },
    "1121": {
      "FaceURL": "https://steamusercontent-a.akamaihd.net/ugc/2050875404517265159/03EE2336D2470B3E645CAE3A77FC34BA137743CA/",
      "BackURL": "https://steamusercontent-a.akamaihd.net/ugc/2050875404517258684/87EDE083E71BACAF74032674A28DCBE65DAFB171/",
      "NumWidth": 1,
      "NumHeight": 1,
      "BackIsHidden": false,
      "UniqueBack": false,
      "Type": 0
    },
    "1122": {
      "FaceURL": "https://steamusercontent-a.akamaihd.net/ugc/2050875404517265863/96AE454A80E1FCD2CA91FBB87DCD8B6AB342D2E7/",
      "BackURL": "https://steamusercontent-a.akamaihd.net/ugc/2050875404517258684/87EDE083E71BACAF74032674A28DCBE65DAFB171/",
      "NumWidth": 1,
      "NumHeight": 1,
      "BackIsHidden": false,
      "UniqueBack": false,
      "Type": 0
    },
    "1123": {
      "FaceURL": "https://steamusercontent-a.akamaihd.net/ugc/2050875404517266093/9F2063F37C1E7FFE2BD8D20FFCD563351C200005/",
      "BackURL": "https://steamusercontent-a.akamaihd.net/ugc/2050875404517258684/87EDE083E71BACAF74032674A28DCBE65DAFB171/",
      "NumWidth": 1,
      "NumHeight": 1,
      "BackIsHidden": false,
      "UniqueBack": false,
      "Type": 0
    },
    "1124": {
      "FaceURL": "https://steamusercontent-a.akamaihd.net/ugc/2050875404517267170/56B5F4D2C8429E589CBC45AE1B67D23CCBE8E4A1/",
      "BackURL": "https://steamusercontent-a.akamaihd.net/ugc/2050875404517258684/87EDE083E71BACAF74032674A28DCBE65DAFB171/",
      "NumWidth": 1,
      "NumHeight": 1,
      "BackIsHidden": false,
      "UniqueBack": false,
      "Type": 0
    },
    "1125": {
      "FaceURL": "https://steamusercontent-a.akamaihd.net/ugc/2050875404517266723/837B49E65ABBFB96BE35105A0BEBFBDA7C2CE80F/",
      "BackURL": "https://steamusercontent-a.akamaihd.net/ugc/2050875404517258684/87EDE083E71BACAF74032674A28DCBE65DAFB171/",
      "NumWidth": 1,
      "NumHeight": 1,
      "BackIsHidden": false,
      "UniqueBack": false,
      "Type": 0
    },
    "1126": {
      "FaceURL": "https://steamusercontent-a.akamaihd.net/ugc/2050875404517268353/98F72EA22C6A20792123379FB0A92DDF95D3542A/",
      "BackURL": "https://steamusercontent-a.akamaihd.net/ugc/2050875404517258684/87EDE083E71BACAF74032674A28DCBE65DAFB171/",
      "NumWidth": 1,
      "NumHeight": 1,
      "BackIsHidden": false,
      "UniqueBack": false,
      "Type": 0
    },
    "1127": {
      "FaceURL": "https://steamusercontent-a.akamaihd.net/ugc/2050875404517267781/E8797D24C7C0ACF9391909879BFE8544FE6A26EA/",
      "BackURL": "https://steamusercontent-a.akamaihd.net/ugc/2050875404517258684/87EDE083E71BACAF74032674A28DCBE65DAFB171/",
      "NumWidth": 1,
      "NumHeight": 1,
      "BackIsHidden": false,
      "UniqueBack": false,
      "Type": 0
    },
    "1128": {
      "FaceURL": "https://steamusercontent-a.akamaihd.net/ugc/2050875404517267594/9BD983F2DDF4A3657DD000C5703272FCEE0EB952/",
      "BackURL": "https://steamusercontent-a.akamaihd.net/ugc/2050875404517258684/87EDE083E71BACAF74032674A28DCBE65DAFB171/",
      "NumWidth": 1,
      "NumHeight": 1,
      "BackIsHidden": false,
      "UniqueBack": false,
      "Type": 0
    },
    "1129": {
      "FaceURL": "https://steamusercontent-a.akamaihd.net/ugc/2050875404517266333/013ACD3844609F46C6288F53B0F462C25CA2D67F/",
      "BackURL": "https://steamusercontent-a.akamaihd.net/ugc/2050875404517258684/87EDE083E71BACAF74032674A28DCBE65DAFB171/",
      "NumWidth": 1,
      "NumHeight": 1,
      "BackIsHidden": false,
      "UniqueBack": false,
      "Type": 0
    }
  }
}
