{
  "Name": "Card",
  "Transform": {
    "posX": -41.70000076293945,
    "posY": 1.1043000221252441,
    "posZ": 28.860000610351562,
    "rotX": 0.0,
    "rotY": 180.0,
    "rotZ": 0.0,
    "scaleX": 1.5299999713897705,
    "scaleY": 1.0,
    "scaleZ": 1.5299999713897705
  },
  "Nickname": "Fire and Flood",
  "Description": "",
  "GMNotes": "",
  "ColorDiffuse": {
    "r": 0.7131999731063843,
    "g": 0.7131999731063843,
    "b": 0.7131999731063843
  },
  "Tags": [
    "Major",
    "Slow"
  ],
  "LayoutGroupSortIndex": 0,
  "Value": 0,
  "Locked": false,
  "Grid": false,
  "Snap": true,
  "IgnoreFoW": false,
  "MeasureMovement": false,
  "DragSelectable": true,
  "Autoraise": true,
  "Sticky": true,
  "Tooltip": true,
  "GridProjection": false,
  "HideWhenFaceDown": true,
  "Hands": true,
  "CardID": 58304,
  "SidewaysCard": false
}
