{
  "Name": "Custom_Tile",
  "Transform": {
    "posX": 38.6449,
    "posY": 1.0921,
    "posZ": 83.96,
    "rotX": 0.0045,
    "rotY": 180.0,
    "rotZ": 180.0,
    "scaleX": 5.46,
    "scaleY": 1.0,
    "scaleZ": 5.46
  },
  "Nickname": "Volcano Looming High",
  "Description": "JE",
  "GMNotes": "",
  "ColorDiffuse": {
    "r": 0.2003,
    "g": 0.1603,
    "b": 0.1518
  },
  "Tags": [
    "JE",
    "Moderate",
    "Spirit"
  ],
  "LayoutGroupSortIndex": 0,
  "Value": 0,
  "Locked": true,
  "Grid": true,
  "Snap": true,
  "IgnoreFoW": false,
  "MeasureMovement": false,
  "DragSelectable": true,
  "Autoraise": true,
  "Sticky": true,
  "Tooltip": true,
  "GridProjection": false,
  "HideWhenFaceDown": false,
  "Hands": false,
  "CustomImage": {
    "ImageURL": "http://cloud-3.steamusercontent.com/ugc/1617312248752032415/22942DBD41EFFFC38398F2375A32B14001CF1798/",
    "ImageSecondaryURL": "http://cloud-3.steamusercontent.com/ugc/1617312248752037490/A99328AFC5A11FEF41FBB4545292CE7A26B4E72C/",
    "ImageScalar": 1.0,
    "WidthScale": 0.0,
    "CustomTile": {
      "Type": 0,
      "Thickness": 0.2,
      "Stackable": false,
      "Stretch": true
    }
  },
  "AttachedSnapPoints": [
    {
      "Position": {
        "x": 0.0176,
        "y": 0.2,
        "z": -0.4246
      }
    },
    {
      "Position": {
        "x": 0.018,
        "y": 0.2,
        "z": -0.16
      }
    },
    {
      "Position": {
        "x": -1.3514,
        "y": 0.2,
        "z": -0.1518
      }
    },
    {
      "Position": {
        "x": -1.1222,
        "y": 0.2,
        "z": -0.1596
      }
    },
    {
      "Position": {
        "x": -0.8947,
        "y": 0.2,
        "z": -0.1545
      }
    },
    {
      "Position": {
        "x": -0.6636,
        "y": 0.2,
        "z": -0.1516
      }
    },
    {
      "Position": {
        "x": -0.4393,
        "y": 0.2,
        "z": -0.1523
      }
    },
    {
      "Position": {
        "x": -0.2103,
        "y": 0.2,
        "z": -0.1551
      }
    },
    {
      "Position": {
        "x": -0.4377,
        "y": 0.2,
        "z": -0.4251
      }
    },
    {
      "Position": {
        "x": -0.6667,
        "y": 0.2,
        "z": -0.424
      }
    },
    {
      "Position": {
        "x": -0.8908,
        "y": 0.2,
        "z": -0.4288
      }
    },
    {
      "Position": {
        "x": -0.2123,
        "y": 0.2,
        "z": -0.427
      }
    }
  ]
}
