{
  "Name": "Custom_Model",
  "Transform": {
    "posX": 100.160400390625,
    "posY": 1.1735999584197998,
    "posZ": 9.468000411987305,
    "rotX": 0.0,
    "rotY": 180.00100708007812,
    "rotZ": 0.0,
    "scaleX": 2.0999999046325684,
    "scaleY": 1.0,
    "scaleZ": 2.0999999046325684
  },
  "Nickname": "H8",
  "Description": "",
  "GMNotes": "",
  "AltLookAngle": {
    "x": 0.0,
    "y": 0.0,
    "z": 0.0
  },
  "ColorDiffuse": {
    "r": 1.0,
    "g": 1.0,
    "b": 1.0
  },
  "LayoutGroupSortIndex": 0,
  "Value": 0,
  "Locked": false,
  "Grid": false,
  "Snap": false,
  "IgnoreFoW": false,
  "MeasureMovement": false,
  "DragSelectable": false,
  "Autoraise": true,
  "Sticky": true,
  "Tooltip": true,
  "GridProjection": false,
  "HideWhenFaceDown": false,
  "Hands": false,
  "CustomMesh": {
    "MeshURL": "http://cloud-3.steamusercontent.com/ugc/2365021141197801842/3784F42423C8A42AD662B36DF191D123CB8D2AC6/",
    "DiffuseURL": "http://cloud-3.steamusercontent.com/ugc/1756938796033607290/C1F6EDFD833D0B18691BE154A33AB2235A85D812/",
    "NormalURL": "",
    "ColliderURL": "http://cloud-3.steamusercontent.com/ugc/2365021141197801842/3784F42423C8A42AD662B36DF191D123CB8D2AC6/",
    "Convex": false,
    "MaterialIndex": 3,
    "TypeIndex": 0,
    "CustomShader": {
      "SpecularColor": {
        "r": 1.0,
        "g": 1.0,
        "b": 1.0
      },
      "SpecularIntensity": 0.0,
      "SpecularSharpness": 2.0,
      "FresnelStrength": 0.0
    },
    "CastShadows": true
  }
}
