{
  "thresholds": [
    {
      "elements": "02010000",
      "position": {
        "x": 1.02,
        "y": 0,
        "z": -0.5
      }
    },
    {
      "elements": "02000002",
      "position": {
        "x": 1.02,
        "y": 0,
        "z": -0.25
      }
    },
    {
      "elements": "03020001",
      "position": {
        "x": 1.02,
        "y": 0,
        "z": 0.1
      }
    },
    {
      "elements": "04030002",
      "position": {
        "x": 1.02,
        "y": 0,
        "z": 0.41
      }
    }
  ]
}
