{
  "Name": "Custom_Model",
  "Transform": {
    "posX": 78.28790283203125,
    "posY": 1.0195000171661377,
    "posZ": -13.205699920654297,
    "rotX": 0.0,
    "rotY": 0.021800000220537186,
    "rotZ": -9.999999747378752e-05,
    "scaleX": 0.8999999761581421,
    "scaleY": 0.8999999761581421,
    "scaleZ": 0.8999999761581421
  },
  "Nickname": "Orange's Defend",
  "Description": "Guard a land against the Invaders. Reduces the Damage done by the Invaders to the land/Dahan by a specified amount.",
  "GMNotes": "",
  "ColorDiffuse": {
    "r": 1.0,
    "g": 0.5929999947547913,
    "b": 0.1607999950647354
  },
  "Tags": [
    "Destroy",
    "Reminder Token"
  ],
  "LayoutGroupSortIndex": 0,
  "Value": 0,
  "Locked": false,
  "Grid": false,
  "Snap": false,
  "IgnoreFoW": false,
  "MeasureMovement": false,
  "DragSelectable": true,
  "Autoraise": true,
  "Sticky": true,
  "Tooltip": true,
  "GridProjection": false,
  "HideWhenFaceDown": false,
  "Hands": true,
  "CustomMesh": {
    "MeshURL": "http://cloud-3.steamusercontent.com/ugc/1749061746121830431/DE000E849E99F439C3775E5C92E327CE09E4DB65/",
    "DiffuseURL": "http://cloud-3.steamusercontent.com/ugc/1752434924170706662/37F12EB9D68832E2A4292A7DD2309A767066C5B1/",
    "NormalURL": "",
    "ColliderURL": "",
    "Convex": true,
    "MaterialIndex": 1,
    "TypeIndex": 0,
    "CastShadows": true
  },
  "States": {
    "2": {
      "GUID": "4e97f3",
      "Name": "Custom_Model",
      "Transform": {
        "posX": -20.88610076904297,
        "posY": 0.05000000074505806,
        "posZ": 2.1438000202178955,
        "rotX": 0.0,
        "rotY": 180.0175018310547,
        "rotZ": 0.0,
        "scaleX": 0.8999999761581421,
        "scaleY": 0.8999999761581421,
        "scaleZ": 0.8999999761581421
      },
      "Nickname": "Orange's Defend",
      "Description": "Guard a land against the Invaders. Reduces the Damage done by the Invaders to the land/Dahan by a specified amount.",
      "GMNotes": "",
      "ColorDiffuse": {
        "r": 1.0,
        "g": 0.5929999947547913,
        "b": 0.1607999950647354
      },
      "Tags": [
        "Destroy",
        "Reminder Token"
      ],
      "LayoutGroupSortIndex": 0,
      "Value": 0,
      "Locked": false,
      "Grid": false,
      "Snap": false,
      "IgnoreFoW": false,
      "MeasureMovement": false,
      "DragSelectable": true,
      "Autoraise": true,
      "Sticky": true,
      "Tooltip": true,
      "GridProjection": false,
      "HideWhenFaceDown": false,
      "Hands": true,
      "CustomMesh": {
        "MeshURL": "http://cloud-3.steamusercontent.com/ugc/1749061746121830431/DE000E849E99F439C3775E5C92E327CE09E4DB65/",
        "DiffuseURL": "http://cloud-3.steamusercontent.com/ugc/1752434998239416952/A5C04560A7C7D4568F12B5B22F8C79E20DA97AD4/",
        "NormalURL": "",
        "ColliderURL": "",
        "Convex": true,
        "MaterialIndex": 1,
        "TypeIndex": 0,
        "CastShadows": true
      },
      "LuaScript": "",
      "LuaScriptState": "",
      "XmlUI": ""
    },
    "3": {
      "GUID": "b467a4",
      "Name": "Custom_Model",
      "Transform": {
        "posX": -18.826200485229492,
        "posY": 0.05000000074505806,
        "posZ": 2.1285998821258545,
        "rotX": 0.0,
        "rotY": 180.0153045654297,
        "rotZ": 0.0,
        "scaleX": 0.8999999761581421,
        "scaleY": 0.8999999761581421,
        "scaleZ": 0.8999999761581421
      },
      "Nickname": "Orange's Defend",
      "Description": "Guard a land against the Invaders. Reduces the Damage done by the Invaders to the land/Dahan by a specified amount.",
      "GMNotes": "",
      "ColorDiffuse": {
        "r": 1.0,
        "g": 0.5929999947547913,
        "b": 0.1607999950647354
      },
      "Tags": [
        "Destroy",
        "Reminder Token"
      ],
      "LayoutGroupSortIndex": 0,
      "Value": 0,
      "Locked": false,
      "Grid": false,
      "Snap": false,
      "IgnoreFoW": false,
      "MeasureMovement": false,
      "DragSelectable": true,
      "Autoraise": true,
      "Sticky": true,
      "Tooltip": true,
      "GridProjection": false,
      "HideWhenFaceDown": false,
      "Hands": true,
      "CustomMesh": {
        "MeshURL": "http://cloud-3.steamusercontent.com/ugc/1749061746121830431/DE000E849E99F439C3775E5C92E327CE09E4DB65/",
        "DiffuseURL": "http://cloud-3.steamusercontent.com/ugc/1752434998239417943/7A1A46FB3C6E42A0B2EDA5DA824D1D227CB2C9D3/",
        "NormalURL": "",
        "ColliderURL": "",
        "Convex": true,
        "MaterialIndex": 1,
        "TypeIndex": 0,
        "CastShadows": true
      },
      "LuaScript": "",
      "LuaScriptState": "",
      "XmlUI": ""
    },
    "4": {
      "GUID": "18016f",
      "Name": "Custom_Model",
      "Transform": {
        "posX": -16.765300750732422,
        "posY": 0.05000000074505806,
        "posZ": 2.1740000247955322,
        "rotX": 0.0,
        "rotY": 180.0137939453125,
        "rotZ": 0.0,
        "scaleX": 0.8999999761581421,
        "scaleY": 0.8999999761581421,
        "scaleZ": 0.8999999761581421
      },
      "Nickname": "Orange's Defend",
      "Description": "Guard a land against the Invaders. Reduces the Damage done by the Invaders to the land/Dahan by a specified amount.",
      "GMNotes": "",
      "ColorDiffuse": {
        "r": 1.0,
        "g": 0.5929999947547913,
        "b": 0.1607999950647354
      },
      "Tags": [
        "Destroy",
        "Reminder Token"
      ],
      "LayoutGroupSortIndex": 0,
      "Value": 0,
      "Locked": false,
      "Grid": false,
      "Snap": false,
      "IgnoreFoW": false,
      "MeasureMovement": false,
      "DragSelectable": true,
      "Autoraise": true,
      "Sticky": true,
      "Tooltip": true,
      "GridProjection": false,
      "HideWhenFaceDown": false,
      "Hands": true,
      "CustomMesh": {
        "MeshURL": "http://cloud-3.steamusercontent.com/ugc/1749061746121830431/DE000E849E99F439C3775E5C92E327CE09E4DB65/",
        "DiffuseURL": "http://cloud-3.steamusercontent.com/ugc/1752434998239419091/631262890558109776FBBCA85247DB7B63E1C948/",
        "NormalURL": "",
        "ColliderURL": "",
        "Convex": true,
        "MaterialIndex": 1,
        "TypeIndex": 0,
        "CastShadows": true
      },
      "LuaScript": "",
      "LuaScriptState": "",
      "XmlUI": ""
    },
    "5": {
      "GUID": "54f701",
      "Name": "Custom_Model",
      "Transform": {
        "posX": -14.697699546813965,
        "posY": 0.05000000074505806,
        "posZ": 2.1740000247955322,
        "rotX": 0.0,
        "rotY": 180.0155029296875,
        "rotZ": 0.0,
        "scaleX": 0.8999999761581421,
        "scaleY": 0.8999999761581421,
        "scaleZ": 0.8999999761581421
      },
      "Nickname": "Orange's Defend",
      "Description": "Guard a land against the Invaders. Reduces the Damage done by the Invaders to the land/Dahan by a specified amount.",
      "GMNotes": "",
      "ColorDiffuse": {
        "r": 1.0,
        "g": 0.5929999947547913,
        "b": 0.1607999950647354
      },
      "Tags": [
        "Destroy",
        "Reminder Token"
      ],
      "LayoutGroupSortIndex": 0,
      "Value": 0,
      "Locked": false,
      "Grid": false,
      "Snap": false,
      "IgnoreFoW": false,
      "MeasureMovement": false,
      "DragSelectable": true,
      "Autoraise": true,
      "Sticky": true,
      "Tooltip": true,
      "GridProjection": false,
      "HideWhenFaceDown": false,
      "Hands": true,
      "CustomMesh": {
        "MeshURL": "http://cloud-3.steamusercontent.com/ugc/1749061746121830431/DE000E849E99F439C3775E5C92E327CE09E4DB65/",
        "DiffuseURL": "http://cloud-3.steamusercontent.com/ugc/1752434998239424662/7B918036CE1AC4ECA1D4577A006AFB0C82B9F52B/",
        "NormalURL": "",
        "ColliderURL": "",
        "Convex": true,
        "MaterialIndex": 1,
        "TypeIndex": 0,
        "CastShadows": true
      },
      "LuaScript": "",
      "LuaScriptState": "",
      "XmlUI": ""
    },
    "6": {
      "GUID": "8e78fc",
      "Name": "Custom_Model",
      "Transform": {
        "posX": -12.63010025024414,
        "posY": 0.05000000074505806,
        "posZ": 2.1740000247955322,
        "rotX": 0.0,
        "rotY": 180.0155029296875,
        "rotZ": 0.0,
        "scaleX": 0.8999999761581421,
        "scaleY": 0.8999999761581421,
        "scaleZ": 0.8999999761581421
      },
      "Nickname": "Orange's Defend",
      "Description": "Guard a land against the Invaders. Reduces the Damage done by the Invaders to the land/Dahan by a specified amount.",
      "GMNotes": "",
      "ColorDiffuse": {
        "r": 1.0,
        "g": 0.5929999947547913,
        "b": 0.1607999950647354
      },
      "Tags": [
        "Destroy",
        "Reminder Token"
      ],
      "LayoutGroupSortIndex": 0,
      "Value": 0,
      "Locked": false,
      "Grid": false,
      "Snap": false,
      "IgnoreFoW": false,
      "MeasureMovement": false,
      "DragSelectable": true,
      "Autoraise": true,
      "Sticky": true,
      "Tooltip": true,
      "GridProjection": false,
      "HideWhenFaceDown": false,
      "Hands": true,
      "CustomMesh": {
        "MeshURL": "http://cloud-3.steamusercontent.com/ugc/1749061746121830431/DE000E849E99F439C3775E5C92E327CE09E4DB65/",
        "DiffuseURL": "http://cloud-3.steamusercontent.com/ugc/1752434998239420892/C6B35383C9121D8F8FB5A0455F3762963812A676/",
        "NormalURL": "",
        "ColliderURL": "",
        "Convex": true,
        "MaterialIndex": 1,
        "TypeIndex": 0,
        "CastShadows": true
      },
      "LuaScript": "",
      "LuaScriptState": "",
      "XmlUI": ""
    },
    "7": {
      "GUID": "4f05d8",
      "Name": "Custom_Model",
      "Transform": {
        "posX": -10.5625,
        "posY": 0.05000000074505806,
        "posZ": 2.1738998889923096,
        "rotX": 0.0,
        "rotY": 180.0081024169922,
        "rotZ": 0.0,
        "scaleX": 0.8999999761581421,
        "scaleY": 0.8999999761581421,
        "scaleZ": 0.8999999761581421
      },
      "Nickname": "Orange's Defend",
      "Description": "Guard a land against the Invaders. Reduces the Damage done by the Invaders to the land/Dahan by a specified amount.",
      "GMNotes": "",
      "ColorDiffuse": {
        "r": 1.0,
        "g": 0.5929999947547913,
        "b": 0.1607999950647354
      },
      "Tags": [
        "Destroy",
        "Reminder Token"
      ],
      "LayoutGroupSortIndex": 0,
      "Value": 0,
      "Locked": false,
      "Grid": false,
      "Snap": false,
      "IgnoreFoW": false,
      "MeasureMovement": false,
      "DragSelectable": true,
      "Autoraise": true,
      "Sticky": true,
      "Tooltip": true,
      "GridProjection": false,
      "HideWhenFaceDown": false,
      "Hands": true,
      "CustomMesh": {
        "MeshURL": "http://cloud-3.steamusercontent.com/ugc/1749061746121830431/DE000E849E99F439C3775E5C92E327CE09E4DB65/",
        "DiffuseURL": "http://cloud-3.steamusercontent.com/ugc/1749057496680632550/1FF8BBCE9A786BD94EA18BC16EE919B3F6C2E008/",
        "NormalURL": "",
        "ColliderURL": "",
        "Convex": true,
        "MaterialIndex": 1,
        "TypeIndex": 0,
        "CastShadows": true
      },
      "LuaScript": "",
      "LuaScriptState": "",
      "XmlUI": ""
    },
    "8": {
      "GUID": "ef31f4",
      "Name": "Custom_Model",
      "Transform": {
        "posX": -8.49489974975586,
        "posY": 0.05000000074505806,
        "posZ": 2.1738998889923096,
        "rotX": 0.0,
        "rotY": 180.00779724121094,
        "rotZ": 0.0,
        "scaleX": 0.8999999761581421,
        "scaleY": 0.8999999761581421,
        "scaleZ": 0.8999999761581421
      },
      "Nickname": "Orange's Defend",
      "Description": "Guard a land against the Invaders. Reduces the Damage done by the Invaders to the land/Dahan by a specified amount.",
      "GMNotes": "",
      "ColorDiffuse": {
        "r": 1.0,
        "g": 0.5929999947547913,
        "b": 0.1607999950647354
      },
      "Tags": [
        "Destroy",
        "Reminder Token"
      ],
      "LayoutGroupSortIndex": 0,
      "Value": 0,
      "Locked": false,
      "Grid": false,
      "Snap": false,
      "IgnoreFoW": false,
      "MeasureMovement": false,
      "DragSelectable": true,
      "Autoraise": true,
      "Sticky": true,
      "Tooltip": true,
      "GridProjection": false,
      "HideWhenFaceDown": false,
      "Hands": true,
      "CustomMesh": {
        "MeshURL": "http://cloud-3.steamusercontent.com/ugc/1749061746121830431/DE000E849E99F439C3775E5C92E327CE09E4DB65/",
        "DiffuseURL": "http://cloud-3.steamusercontent.com/ugc/1749057496680637473/42DC69F871E095AD782B24059FE69EF2BF6CFC14/",
        "NormalURL": "",
        "ColliderURL": "",
        "Convex": true,
        "MaterialIndex": 1,
        "TypeIndex": 0,
        "CastShadows": true
      },
      "LuaScript": "",
      "LuaScriptState": "",
      "XmlUI": ""
    },
    "9": {
      "GUID": "1a441b",
      "Name": "Custom_Model",
      "Transform": {
        "posX": -6.427299976348877,
        "posY": 0.05000000074505806,
        "posZ": 2.1738998889923096,
        "rotX": 0.0,
        "rotY": 180.0052032470703,
        "rotZ": 0.0,
        "scaleX": 0.8999999761581421,
        "scaleY": 0.8999999761581421,
        "scaleZ": 0.8999999761581421
      },
      "Nickname": "Orange's Defend",
      "Description": "Guard a land against the Invaders. Reduces the Damage done by the Invaders to the land/Dahan by a specified amount.",
      "GMNotes": "",
      "ColorDiffuse": {
        "r": 1.0,
        "g": 0.5929999947547913,
        "b": 0.1607999950647354
      },
      "Tags": [
        "Destroy",
        "Reminder Token"
      ],
      "LayoutGroupSortIndex": 0,
      "Value": 0,
      "Locked": false,
      "Grid": false,
      "Snap": false,
      "IgnoreFoW": false,
      "MeasureMovement": false,
      "DragSelectable": true,
      "Autoraise": true,
      "Sticky": true,
      "Tooltip": true,
      "GridProjection": false,
      "HideWhenFaceDown": false,
      "Hands": true,
      "CustomMesh": {
        "MeshURL": "http://cloud-3.steamusercontent.com/ugc/1749061746121830431/DE000E849E99F439C3775E5C92E327CE09E4DB65/",
        "DiffuseURL": "http://cloud-3.steamusercontent.com/ugc/1749057496680638930/C288F06421E07AB75EC9D34D66AA35728E75CC59/",
        "NormalURL": "",
        "ColliderURL": "",
        "Convex": true,
        "MaterialIndex": 1,
        "TypeIndex": 0,
        "CastShadows": true
      },
      "LuaScript": "",
      "LuaScriptState": "",
      "XmlUI": ""
    },
    "10": {
      "GUID": "a4b0d5",
      "Name": "Custom_Model",
      "Transform": {
        "posX": -4.359600067138672,
        "posY": 0.05000000074505806,
        "posZ": 2.1738998889923096,
        "rotX": 0.0,
        "rotY": 180.00540161132812,
        "rotZ": 0.0,
        "scaleX": 0.8999999761581421,
        "scaleY": 0.8999999761581421,
        "scaleZ": 0.8999999761581421
      },
      "Nickname": "Orange's Defend",
      "Description": "Guard a land against the Invaders. Reduces the Damage done by the Invaders to the land/Dahan by a specified amount.",
      "GMNotes": "",
      "ColorDiffuse": {
        "r": 1.0,
        "g": 0.5929999947547913,
        "b": 0.1607999950647354
      },
      "Tags": [
        "Destroy",
        "Reminder Token"
      ],
      "LayoutGroupSortIndex": 0,
      "Value": 0,
      "Locked": false,
      "Grid": false,
      "Snap": false,
      "IgnoreFoW": false,
      "MeasureMovement": false,
      "DragSelectable": true,
      "Autoraise": true,
      "Sticky": true,
      "Tooltip": true,
      "GridProjection": false,
      "HideWhenFaceDown": false,
      "Hands": true,
      "CustomMesh": {
        "MeshURL": "http://cloud-3.steamusercontent.com/ugc/1749061746121830431/DE000E849E99F439C3775E5C92E327CE09E4DB65/",
        "DiffuseURL": "http://cloud-3.steamusercontent.com/ugc/1749057496680643307/464FE0E85EC18E3506CA1004A20D054B451EDA20/",
        "NormalURL": "",
        "ColliderURL": "",
        "Convex": true,
        "MaterialIndex": 1,
        "TypeIndex": 0,
        "CastShadows": true
      },
      "LuaScript": "",
      "LuaScriptState": "",
      "XmlUI": ""
    },
    "11": {
      "GUID": "a47db4",
      "Name": "Custom_Model",
      "Transform": {
        "posX": -2.3296000957489014,
        "posY": 0.05000000074505806,
        "posZ": 2.1723999977111816,
        "rotX": 0.0,
        "rotY": 180.00540161132812,
        "rotZ": 0.0,
        "scaleX": 0.8999999761581421,
        "scaleY": 0.8999999761581421,
        "scaleZ": 0.8999999761581421
      },
      "Nickname": "Orange's Defend",
      "Description": "Guard a land against the Invaders. Reduces the Damage done by the Invaders to the land/Dahan by a specified amount.",
      "GMNotes": "",
      "ColorDiffuse": {
        "r": 1.0,
        "g": 0.5929999947547913,
        "b": 0.1607999950647354
      },
      "Tags": [
        "Destroy",
        "Reminder Token"
      ],
      "LayoutGroupSortIndex": 0,
      "Value": 0,
      "Locked": false,
      "Grid": false,
      "Snap": false,
      "IgnoreFoW": false,
      "MeasureMovement": false,
      "DragSelectable": true,
      "Autoraise": true,
      "Sticky": true,
      "Tooltip": true,
      "GridProjection": false,
      "HideWhenFaceDown": false,
      "Hands": true,
      "CustomMesh": {
        "MeshURL": "http://cloud-3.steamusercontent.com/ugc/1749061746121830431/DE000E849E99F439C3775E5C92E327CE09E4DB65/",
        "DiffuseURL": "http://cloud-3.steamusercontent.com/ugc/1749057496680646407/347AF776079EE246E02833DD475D56B8DAD8AEE5/",
        "NormalURL": "",
        "ColliderURL": "",
        "Convex": true,
        "MaterialIndex": 1,
        "TypeIndex": 0,
        "CastShadows": true
      },
      "LuaScript": "",
      "LuaScriptState": "",
      "XmlUI": ""
    },
    "12": {
      "GUID": "cf3b7a",
      "Name": "Custom_Model",
      "Transform": {
        "posX": -0.2240999937057495,
        "posY": 0.05000000074505806,
        "posZ": 2.1740000247955322,
        "rotX": 0.0,
        "rotY": 180.0153045654297,
        "rotZ": 0.0,
        "scaleX": 0.8999999761581421,
        "scaleY": 0.8999999761581421,
        "scaleZ": 0.8999999761581421
      },
      "Nickname": "Orange's Defend",
      "Description": "Guard a land against the Invaders. Reduces the Damage done by the Invaders to the land/Dahan by a specified amount.",
      "GMNotes": "",
      "ColorDiffuse": {
        "r": 1.0,
        "g": 0.5929999947547913,
        "b": 0.1607999950647354
      },
      "Tags": [
        "Destroy",
        "Reminder Token"
      ],
      "LayoutGroupSortIndex": 0,
      "Value": 0,
      "Locked": false,
      "Grid": false,
      "Snap": false,
      "IgnoreFoW": false,
      "MeasureMovement": false,
      "DragSelectable": true,
      "Autoraise": true,
      "Sticky": true,
      "Tooltip": true,
      "GridProjection": false,
      "HideWhenFaceDown": false,
      "Hands": true,
      "CustomMesh": {
        "MeshURL": "http://cloud-3.steamusercontent.com/ugc/1749061746121830431/DE000E849E99F439C3775E5C92E327CE09E4DB65/",
        "DiffuseURL": "http://cloud-3.steamusercontent.com/ugc/1749057496680647764/2CB13E50712BF2BEA9455D9714B8C0D9DEF03D11/",
        "NormalURL": "",
        "ColliderURL": "",
        "Convex": true,
        "MaterialIndex": 1,
        "TypeIndex": 0,
        "CastShadows": true
      },
      "LuaScript": "",
      "LuaScriptState": "",
      "XmlUI": ""
    },
    "13": {
      "GUID": "a82b68",
      "Name": "Custom_Model",
      "Transform": {
        "posX": 1.843500018119812,
        "posY": 0.05000000074505806,
        "posZ": 2.1740000247955322,
        "rotX": 0.0,
        "rotY": 180.0153045654297,
        "rotZ": 0.0,
        "scaleX": 0.8999999761581421,
        "scaleY": 0.8999999761581421,
        "scaleZ": 0.8999999761581421
      },
      "Nickname": "Orange's Defend",
      "Description": "Guard a land against the Invaders. Reduces the Damage done by the Invaders to the land/Dahan by a specified amount.",
      "GMNotes": "",
      "ColorDiffuse": {
        "r": 1.0,
        "g": 0.5929999947547913,
        "b": 0.1607999950647354
      },
      "Tags": [
        "Destroy",
        "Reminder Token"
      ],
      "LayoutGroupSortIndex": 0,
      "Value": 0,
      "Locked": false,
      "Grid": false,
      "Snap": false,
      "IgnoreFoW": false,
      "MeasureMovement": false,
      "DragSelectable": true,
      "Autoraise": true,
      "Sticky": true,
      "Tooltip": true,
      "GridProjection": false,
      "HideWhenFaceDown": false,
      "Hands": true,
      "CustomMesh": {
        "MeshURL": "http://cloud-3.steamusercontent.com/ugc/1749061746121830431/DE000E849E99F439C3775E5C92E327CE09E4DB65/",
        "DiffuseURL": "http://cloud-3.steamusercontent.com/ugc/1749057496680648985/36F955A2B0167BF2CFEDCFEF772CE011FD392A0A/",
        "NormalURL": "",
        "ColliderURL": "",
        "Convex": true,
        "MaterialIndex": 1,
        "TypeIndex": 0,
        "CastShadows": true
      },
      "LuaScript": "",
      "LuaScriptState": "",
      "XmlUI": ""
    },
    "14": {
      "GUID": "a1f925",
      "Name": "Custom_Model",
      "Transform": {
        "posX": 3.9112000465393066,
        "posY": 0.05000000074505806,
        "posZ": 2.1738998889923096,
        "rotX": 0.0,
        "rotY": 180.0133056640625,
        "rotZ": 0.0,
        "scaleX": 0.8999999761581421,
        "scaleY": 0.8999999761581421,
        "scaleZ": 0.8999999761581421
      },
      "Nickname": "Orange's Defend",
      "Description": "Guard a land against the Invaders. Reduces the Damage done by the Invaders to the land/Dahan by a specified amount.",
      "GMNotes": "",
      "ColorDiffuse": {
        "r": 1.0,
        "g": 0.5929999947547913,
        "b": 0.1607999950647354
      },
      "Tags": [
        "Destroy",
        "Reminder Token"
      ],
      "LayoutGroupSortIndex": 0,
      "Value": 0,
      "Locked": false,
      "Grid": false,
      "Snap": false,
      "IgnoreFoW": false,
      "MeasureMovement": false,
      "DragSelectable": true,
      "Autoraise": true,
      "Sticky": true,
      "Tooltip": true,
      "GridProjection": false,
      "HideWhenFaceDown": false,
      "Hands": true,
      "CustomMesh": {
        "MeshURL": "http://cloud-3.steamusercontent.com/ugc/1749061746121830431/DE000E849E99F439C3775E5C92E327CE09E4DB65/",
        "DiffuseURL": "http://cloud-3.steamusercontent.com/ugc/1749057496680650668/D511A5956BD87A8BC6A5900D27B49E471FF147F9/",
        "NormalURL": "",
        "ColliderURL": "",
        "Convex": true,
        "MaterialIndex": 1,
        "TypeIndex": 0,
        "CastShadows": true
      },
      "LuaScript": "",
      "LuaScriptState": "",
      "XmlUI": ""
    },
    "15": {
      "GUID": "e64d90",
      "Name": "Custom_Model",
      "Transform": {
        "posX": 5.978799819946289,
        "posY": 0.05000000074505806,
        "posZ": 2.1738998889923096,
        "rotX": 0.0,
        "rotY": 180.01319885253906,
        "rotZ": 0.0,
        "scaleX": 0.8999999761581421,
        "scaleY": 0.8999999761581421,
        "scaleZ": 0.8999999761581421
      },
      "Nickname": "Orange's Defend",
      "Description": "Guard a land against the Invaders. Reduces the Damage done by the Invaders to the land/Dahan by a specified amount.",
      "GMNotes": "",
      "ColorDiffuse": {
        "r": 1.0,
        "g": 0.5929999947547913,
        "b": 0.1607999950647354
      },
      "Tags": [
        "Destroy",
        "Reminder Token"
      ],
      "LayoutGroupSortIndex": 0,
      "Value": 0,
      "Locked": false,
      "Grid": false,
      "Snap": false,
      "IgnoreFoW": false,
      "MeasureMovement": false,
      "DragSelectable": true,
      "Autoraise": true,
      "Sticky": true,
      "Tooltip": true,
      "GridProjection": false,
      "HideWhenFaceDown": false,
      "Hands": true,
      "CustomMesh": {
        "MeshURL": "http://cloud-3.steamusercontent.com/ugc/1749061746121830431/DE000E849E99F439C3775E5C92E327CE09E4DB65/",
        "DiffuseURL": "http://cloud-3.steamusercontent.com/ugc/1749057496680651535/BECAAFE8F9E01B301647CD4DDEAD60D36D3BBA01/",
        "NormalURL": "",
        "ColliderURL": "",
        "Convex": true,
        "MaterialIndex": 1,
        "TypeIndex": 0,
        "CastShadows": true
      },
      "LuaScript": "",
      "LuaScriptState": "",
      "XmlUI": ""
    },
    "16": {
      "GUID": "b6a5ef",
      "Name": "Custom_Model",
      "Transform": {
        "posX": 8.046500205993652,
        "posY": 0.05000000074505806,
        "posZ": 2.1738998889923096,
        "rotX": 0.0,
        "rotY": 180.01319885253906,
        "rotZ": 0.0,
        "scaleX": 0.8999999761581421,
        "scaleY": 0.8999999761581421,
        "scaleZ": 0.8999999761581421
      },
      "Nickname": "Orange's Defend",
      "Description": "Guard a land against the Invaders. Reduces the Damage done by the Invaders to the land/Dahan by a specified amount.",
      "GMNotes": "",
      "ColorDiffuse": {
        "r": 1.0,
        "g": 0.5929999947547913,
        "b": 0.1607999950647354
      },
      "Tags": [
        "Destroy",
        "Reminder Token"
      ],
      "LayoutGroupSortIndex": 0,
      "Value": 0,
      "Locked": false,
      "Grid": false,
      "Snap": false,
      "IgnoreFoW": false,
      "MeasureMovement": false,
      "DragSelectable": true,
      "Autoraise": true,
      "Sticky": true,
      "Tooltip": true,
      "GridProjection": false,
      "HideWhenFaceDown": false,
      "Hands": true,
      "CustomMesh": {
        "MeshURL": "http://cloud-3.steamusercontent.com/ugc/1749061746121830431/DE000E849E99F439C3775E5C92E327CE09E4DB65/",
        "DiffuseURL": "http://cloud-3.steamusercontent.com/ugc/1749057496680652526/16D832CFD5521C7C587512F41A7013CCAF40DC1E/",
        "NormalURL": "",
        "ColliderURL": "",
        "Convex": true,
        "MaterialIndex": 1,
        "TypeIndex": 0,
        "CastShadows": true
      },
      "LuaScript": "",
      "LuaScriptState": "",
      "XmlUI": ""
    },
    "17": {
      "GUID": "5c092d",
      "Name": "Custom_Model",
      "Transform": {
        "posX": 10.11400032043457,
        "posY": 0.05000000074505806,
        "posZ": 2.1738998889923096,
        "rotX": 0.0,
        "rotY": 180.0052947998047,
        "rotZ": 0.0,
        "scaleX": 0.8999999761581421,
        "scaleY": 0.8999999761581421,
        "scaleZ": 0.8999999761581421
      },
      "Nickname": "Orange's Defend",
      "Description": "Guard a land against the Invaders. Reduces the Damage done by the Invaders to the land/Dahan by a specified amount.",
      "GMNotes": "",
      "ColorDiffuse": {
        "r": 1.0,
        "g": 0.5929999947547913,
        "b": 0.1607999950647354
      },
      "Tags": [
        "Destroy",
        "Reminder Token"
      ],
      "LayoutGroupSortIndex": 0,
      "Value": 0,
      "Locked": false,
      "Grid": false,
      "Snap": false,
      "IgnoreFoW": false,
      "MeasureMovement": false,
      "DragSelectable": true,
      "Autoraise": true,
      "Sticky": true,
      "Tooltip": true,
      "GridProjection": false,
      "HideWhenFaceDown": false,
      "Hands": true,
      "CustomMesh": {
        "MeshURL": "http://cloud-3.steamusercontent.com/ugc/1749061746121830431/DE000E849E99F439C3775E5C92E327CE09E4DB65/",
        "DiffuseURL": "http://cloud-3.steamusercontent.com/ugc/1749057496680653412/0B53E622D74277FF1DDB0BF0E698CCCAA4D96B73/",
        "NormalURL": "",
        "ColliderURL": "",
        "Convex": true,
        "MaterialIndex": 1,
        "TypeIndex": 0,
        "CastShadows": true
      },
      "LuaScript": "",
      "LuaScriptState": "",
      "XmlUI": ""
    },
    "18": {
      "GUID": "e76e2d",
      "Name": "Custom_Model",
      "Transform": {
        "posX": 12.181699752807617,
        "posY": 0.05000000074505806,
        "posZ": 2.1738998889923096,
        "rotX": 0.0,
        "rotY": 180.00750732421875,
        "rotZ": 0.0,
        "scaleX": 0.8999999761581421,
        "scaleY": 0.8999999761581421,
        "scaleZ": 0.8999999761581421
      },
      "Nickname": "Orange's Defend",
      "Description": "Guard a land against the Invaders. Reduces the Damage done by the Invaders to the land/Dahan by a specified amount.",
      "GMNotes": "",
      "ColorDiffuse": {
        "r": 1.0,
        "g": 0.5929999947547913,
        "b": 0.1607999950647354
      },
      "Tags": [
        "Destroy",
        "Reminder Token"
      ],
      "LayoutGroupSortIndex": 0,
      "Value": 0,
      "Locked": false,
      "Grid": false,
      "Snap": false,
      "IgnoreFoW": false,
      "MeasureMovement": false,
      "DragSelectable": true,
      "Autoraise": true,
      "Sticky": true,
      "Tooltip": true,
      "GridProjection": false,
      "HideWhenFaceDown": false,
      "Hands": true,
      "CustomMesh": {
        "MeshURL": "http://cloud-3.steamusercontent.com/ugc/1749061746121830431/DE000E849E99F439C3775E5C92E327CE09E4DB65/",
        "DiffuseURL": "http://cloud-3.steamusercontent.com/ugc/1749057496680654412/6074A9C83FC03421DD3EFEE5D347DEDC022ADB1E/",
        "NormalURL": "",
        "ColliderURL": "",
        "Convex": true,
        "MaterialIndex": 1,
        "TypeIndex": 0,
        "CastShadows": true
      },
      "LuaScript": "",
      "LuaScriptState": "",
      "XmlUI": ""
    },
    "19": {
      "GUID": "a745f4",
      "Name": "Custom_Model",
      "Transform": {
        "posX": 14.249300003051758,
        "posY": 0.05000000074505806,
        "posZ": 2.1738998889923096,
        "rotX": 0.0,
        "rotY": 180.00819396972656,
        "rotZ": 0.0,
        "scaleX": 0.8999999761581421,
        "scaleY": 0.8999999761581421,
        "scaleZ": 0.8999999761581421
      },
      "Nickname": "Orange's Defend",
      "Description": "Guard a land against the Invaders. Reduces the Damage done by the Invaders to the land/Dahan by a specified amount.",
      "GMNotes": "",
      "ColorDiffuse": {
        "r": 1.0,
        "g": 0.5929999947547913,
        "b": 0.1607999950647354
      },
      "Tags": [
        "Destroy",
        "Reminder Token"
      ],
      "LayoutGroupSortIndex": 0,
      "Value": 0,
      "Locked": false,
      "Grid": false,
      "Snap": false,
      "IgnoreFoW": false,
      "MeasureMovement": false,
      "DragSelectable": true,
      "Autoraise": true,
      "Sticky": true,
      "Tooltip": true,
      "GridProjection": false,
      "HideWhenFaceDown": false,
      "Hands": true,
      "CustomMesh": {
        "MeshURL": "http://cloud-3.steamusercontent.com/ugc/1749061746121830431/DE000E849E99F439C3775E5C92E327CE09E4DB65/",
        "DiffuseURL": "http://cloud-3.steamusercontent.com/ugc/1749057496680655320/4752298B0D66FD7647BA5FA7774895DADDB09563/",
        "NormalURL": "",
        "ColliderURL": "",
        "Convex": true,
        "MaterialIndex": 1,
        "TypeIndex": 0,
        "CastShadows": true
      },
      "LuaScript": "",
      "LuaScriptState": "",
      "XmlUI": ""
    },
    "20": {
      "GUID": "47c437",
      "Name": "Custom_Model",
      "Transform": {
        "posX": 16.317100524902344,
        "posY": 0.05000000074505806,
        "posZ": 2.1738998889923096,
        "rotX": 0.0,
        "rotY": 180.00830078125,
        "rotZ": 0.0,
        "scaleX": 0.8999999761581421,
        "scaleY": 0.8999999761581421,
        "scaleZ": 0.8999999761581421
      },
      "Nickname": "Orange's Defend",
      "Description": "Guard a land against the Invaders. Reduces the Damage done by the Invaders to the land/Dahan by a specified amount.",
      "GMNotes": "",
      "ColorDiffuse": {
        "r": 1.0,
        "g": 0.5929999947547913,
        "b": 0.1607999950647354
      },
      "Tags": [
        "Destroy",
        "Reminder Token"
      ],
      "LayoutGroupSortIndex": 0,
      "Value": 0,
      "Locked": false,
      "Grid": false,
      "Snap": false,
      "IgnoreFoW": false,
      "MeasureMovement": false,
      "DragSelectable": true,
      "Autoraise": true,
      "Sticky": true,
      "Tooltip": true,
      "GridProjection": false,
      "HideWhenFaceDown": false,
      "Hands": true,
      "CustomMesh": {
        "MeshURL": "http://cloud-3.steamusercontent.com/ugc/1749061746121830431/DE000E849E99F439C3775E5C92E327CE09E4DB65/",
        "DiffuseURL": "http://cloud-3.steamusercontent.com/ugc/1749057496680656424/340BB9951AF477B3A2FC169FD7368F281A12B092/",
        "NormalURL": "",
        "ColliderURL": "",
        "Convex": true,
        "MaterialIndex": 1,
        "TypeIndex": 0,
        "CastShadows": true
      },
      "LuaScript": "",
      "LuaScriptState": "",
      "XmlUI": ""
    },
    "21": {
      "GUID": "c052a8",
      "Name": "Custom_Model",
      "Transform": {
        "posX": 18.42300033569336,
        "posY": 0.05000000074505806,
        "posZ": 2.1317999362945557,
        "rotX": 0.0,
        "rotY": 180.0135955810547,
        "rotZ": 0.0,
        "scaleX": 0.8999999761581421,
        "scaleY": 0.8999999761581421,
        "scaleZ": 0.8999999761581421
      },
      "Nickname": "Orange's Defend",
      "Description": "Guard a land against the Invaders. Reduces the Damage done by the Invaders to the land/Dahan by a specified amount",
      "GMNotes": "",
      "ColorDiffuse": {
        "r": 1.0,
        "g": 0.5929999947547913,
        "b": 0.1607999950647354
      },
      "Tags": [
        "Destroy",
        "Reminder Token"
      ],
      "LayoutGroupSortIndex": 0,
      "Value": 0,
      "Locked": false,
      "Grid": false,
      "Snap": false,
      "IgnoreFoW": false,
      "MeasureMovement": false,
      "DragSelectable": true,
      "Autoraise": true,
      "Sticky": true,
      "Tooltip": true,
      "GridProjection": false,
      "HideWhenFaceDown": false,
      "Hands": true,
      "CustomMesh": {
        "MeshURL": "http://cloud-3.steamusercontent.com/ugc/1749061746121830431/DE000E849E99F439C3775E5C92E327CE09E4DB65/",
        "DiffuseURL": "http://cloud-3.steamusercontent.com/ugc/1753560381472353118/3A1F6CF1B4B7E307663687973E8B4B7CB04127BB/",
        "NormalURL": "",
        "ColliderURL": "",
        "Convex": true,
        "MaterialIndex": 1,
        "TypeIndex": 5,
        "CastShadows": true
      },
      "LuaScript": "",
      "LuaScriptState": "",
      "XmlUI": ""
    }
  }
}
