{
  "Name": "CardCustom",
  "Transform": {
    "posX": 90.28140258789062,
    "posY": 26.640100479125977,
    "posZ": 102.13619995117188,
    "rotX": 0.0,
    "rotY": 180.0,
    "rotZ": 180.0,
    "scaleX": 1.5299999713897705,
    "scaleY": 1.0,
    "scaleZ": 1.5299999713897705
  },
  "Nickname": "Swallowed by the Endless Dark",
  "Description": "",
  "GMNotes": "",
  "AltLookAngle": {
    "x": 0.0,
    "y": 0.0,
    "z": 0.0
  },
  "ColorDiffuse": {
    "r": 0.7131999731063843,
    "g": 0.7131999731063843,
    "b": 0.7131999731063843
  },
  "Tags": [
    "Fast",
    "Unique"
  ],
  "LayoutGroupSortIndex": 0,
  "Value": 0,
  "Locked": false,
  "Grid": false,
  "Snap": true,
  "IgnoreFoW": false,
  "MeasureMovement": false,
  "DragSelectable": true,
  "Autoraise": true,
  "Sticky": true,
  "Tooltip": true,
  "GridProjection": false,
  "HideWhenFaceDown": true,
  "Hands": true,
  "CardID": 258500,
  "SidewaysCard": false,
  "CustomDeck": {
    "2585": {
      "FaceURL": "https://steamusercontent-a.akamaihd.net/ugc/2308724646351076214/3667C756DFD74D91EF386AEC510C691C5986FC0F/",
      "BackURL": "https://steamusercontent-a.akamaihd.net/ugc/2308724646351076774/33E86FF24E3C0E766173BC9DE2D2B67343C7D2DD/",
      "NumWidth": 1,
      "NumHeight": 1,
      "BackIsHidden": true,
      "UniqueBack": false,
      "Type": 0
    }
  }
}
