{
  "Name": "Deck",
  "Transform": {
    "posX": -72.60521,
    "posY": 1.13580656,
    "posZ": 17.98,
    "rotX": 0.00444678543,
    "rotY": 180.000122,
    "rotZ": 180.0,
    "scaleX": 1.3107506,
    "scaleY": 1.0,
    "scaleZ": 1.3107506
  },
  "Nickname": "",
  "Description": "",
  "GMNotes": "",
  "ColorDiffuse": {
    "r": 0.713235259,
    "g": 0.713235259,
    "b": 0.713235259
  },
  "Locked": false,
  "Grid": true,
  "Snap": true,
  "IgnoreFoW": false,
  "MeasureMovement": false,
  "DragSelectable": true,
  "Autoraise": true,
  "Sticky": true,
  "Tooltip": true,
  "GridProjection": false,
  "HideWhenFaceDown": true,
  "Hands": false,
  "SidewaysCard": false,
  "DeckIDs": [
    45304,
    45303,
    45302,
    45301,
    45300
  ],
  "CustomDeck": {
    "453": {
      "FaceURL": "http://cloud-3.steamusercontent.com/ugc/1461933821420796751/403E44B71C144490B656E5F069BA4684DC25E764/",
      "BackURL": "http://cloud-3.steamusercontent.com/ugc/1461933821420809855/37B4AE98CF4B0B5750665F375B0DD1FF87F60DA4/",
      "NumWidth": 3,
      "NumHeight": 2,
      "BackIsHidden": true,
      "UniqueBack": false,
      "Type": 0
    }
  }
}
