{
  "Name": "Custom_Token",
  "Transform": {
    "posX": -62.4619446,
    "posY": 0.5980168,
    "posZ": 49.0513,
    "rotX": -1.03995035e-06,
    "rotY": 150.0,
    "rotZ": -0.000144544887,
    "scaleX": 0.8,
    "scaleY": 1.0,
    "scaleZ": 0.8
  },
  "Nickname": "",
  "Description": "",
  "GMNotes": "",
  "ColorDiffuse": {
    "r": 0.831372559,
    "g": 0.831372559,
    "b": 0.831372559
  },
  "Locked": true,
  "Grid": false,
  "Snap": true,
  "IgnoreFoW": false,
  "MeasureMovement": false,
  "DragSelectable": true,
  "Autoraise": true,
  "Sticky": true,
  "Tooltip": true,
  "GridProjection": false,
  "HideWhenFaceDown": false,
  "Hands": false,
  "CustomImage": {
    "ImageURL": "http://cloud-3.steamusercontent.com/ugc/1284038874063612450/EB089C5FDB6BECAE835093D45CD68E8B47D63283/",
    "ImageSecondaryURL": "",
    "ImageScalar": 1.0,
    "WidthScale": 0.0,
    "CustomToken": {
      "Thickness": 0.3950002,
      "MergeDistancePixels": 15.0,
      "StandUp": false,
      "Stackable": false
    }
  },
  "LuaScriptState": "",
  "XmlUI": ""
}