{
  "Name": "BlockSquare",
  "Transform": {
    "posX": 30.5700111,
    "posY": 0.8,
    "posZ": -6.65757561,
    "rotX": 0.0,
    "rotY": -0.00371260056,
    "rotZ": 0.0,
    "scaleX": 174.11,
    "scaleY": 0.3,
    "scaleZ": 2.09
  },
  "Nickname": "",
  "Description": "",
  "GMNotes": "",
  "ColorDiffuse": {
    "r": 0.08235239,
    "g": 0.0588230565,
    "b": 0.0392156877
  },
  "LayoutGroupSortIndex": 0,
  "Value": 0,
  "Locked": true,
  "Grid": true,
  "Snap": true,
  "IgnoreFoW": false,
  "MeasureMovement": false,
  "DragSelectable": true,
  "Autoraise": true,
  "Sticky": true,
  "Tooltip": true,
  "GridProjection": false,
  "HideWhenFaceDown": false,
  "Hands": false
}
