{
  "Name": "Custom_Model",
  "Transform": {
    "posX": 106.1494,
    "posY": 2.6865,
    "posZ": 15.9325,
    "rotX": 0.0625,
    "rotY": 359.9929,
    "rotZ": 0.0039,
    "scaleX": 1.0,
    "scaleY": 1.0,
    "scaleZ": 1.0
  },
  "Nickname": "City",
  "Description": "",
  "GMNotes": "",
  "AltLookAngle": {
    "x": 0.0,
    "y": 0.0,
    "z": 0.0
  },
  "ColorDiffuse": {
    "r": 0.8721,
    "g": 0.8721,
    "b": 0.8721
  },
  "Tags": [
    "City",
    "Highlight"
  ],
  "LayoutGroupSortIndex": 0,
  "Value": 0,
  "Locked": false,
  "Grid": false,
  "Snap": true,
  "IgnoreFoW": false,
  "MeasureMovement": false,
  "DragSelectable": true,
  "Autoraise": true,
  "Sticky": true,
  "Tooltip": true,
  "GridProjection": false,
  "HideWhenFaceDown": false,
  "Hands": false,
  "CustomMesh": {
    "MeshURL": "https://steamusercontent-a.akamaihd.net/ugc/1761463413139116026/6C80E8EBD28F1C7E8E816024BD7512FFDF676E13/",
    "DiffuseURL": "",
    "NormalURL": "",
    "ColliderURL": "",
    "Convex": true,
    "MaterialIndex": 0,
    "TypeIndex": 1,
    "CustomShader": {
      "SpecularColor": {
        "r": 1.0,
        "g": 1.0,
        "b": 1.0
      },
      "SpecularIntensity": 0.0,
      "SpecularSharpness": 7.0,
      "FresnelStrength": 0.4
    },
    "CastShadows": true
  },
  "AttachedSnapPoints": [
    {
      "Position": {
        "x": 0.0004,
        "y": 2.59,
        "z": -0.0001
      }
    }
  ],
  "States": {
    "2": {
      "GUID": "c9d47d",
      "Name": "Custom_Model",
      "Transform": {
        "posX": -26.4502,
        "posY": 0.96,
        "posZ": -1.5124,
        "rotX": 0.0,
        "rotY": 179.9978,
        "rotZ": 0.0,
        "scaleX": 1.0,
        "scaleY": 1.0,
        "scaleZ": 1.0
      },
      "Nickname": "City",
      "Description": "",
      "GMNotes": "",
      "AltLookAngle": {
        "x": 0.0,
        "y": 0.0,
        "z": 0.0
      },
      "ColorDiffuse": {
        "r": 0.8721,
        "g": 0.8721,
        "b": 0.8721
      },
      "Tags": [
        "City",
        "Highlight"
      ],
      "LayoutGroupSortIndex": 0,
      "Value": 0,
      "Locked": false,
      "Grid": false,
      "Snap": true,
      "IgnoreFoW": false,
      "MeasureMovement": false,
      "DragSelectable": true,
      "Autoraise": true,
      "Sticky": true,
      "Tooltip": true,
      "GridProjection": false,
      "HideWhenFaceDown": false,
      "Hands": false,
      "CustomMesh": {
        "MeshURL": "https://steamusercontent-a.akamaihd.net/ugc/1761463413139116026/6C80E8EBD28F1C7E8E816024BD7512FFDF676E13/",
        "DiffuseURL": "",
        "NormalURL": "",
        "ColliderURL": "",
        "Convex": true,
        "MaterialIndex": 0,
        "TypeIndex": 1,
        "CustomShader": {
          "SpecularColor": {
            "r": 1.0,
            "g": 1.0,
            "b": 1.0
          },
          "SpecularIntensity": 0.0,
          "SpecularSharpness": 7.0,
          "FresnelStrength": 0.4
        },
        "CastShadows": true
      },
      "LuaScript": "",
      "LuaScriptState": "",
      "XmlUI": "",
      "AttachedSnapPoints": [
        {
          "Position": {
            "x": 0.0004,
            "y": 2.59,
            "z": -0.0001
          }
        }
      ]
    },
    "3": {
      "GUID": "c0d20d",
      "Name": "Custom_Model",
      "Transform": {
        "posX": -24.0914,
        "posY": 0.96,
        "posZ": -1.2882,
        "rotX": 0.0,
        "rotY": 179.9978,
        "rotZ": 0.0,
        "scaleX": 1.0,
        "scaleY": 1.0,
        "scaleZ": 1.0
      },
      "Nickname": "City",
      "Description": "",
      "GMNotes": "",
      "AltLookAngle": {
        "x": 0.0,
        "y": 0.0,
        "z": 0.0
      },
      "ColorDiffuse": {
        "r": 0.8721,
        "g": 0.8721,
        "b": 0.8721
      },
      "Tags": [
        "City",
        "Highlight"
      ],
      "LayoutGroupSortIndex": 0,
      "Value": 0,
      "Locked": false,
      "Grid": false,
      "Snap": true,
      "IgnoreFoW": false,
      "MeasureMovement": false,
      "DragSelectable": true,
      "Autoraise": true,
      "Sticky": true,
      "Tooltip": true,
      "GridProjection": false,
      "HideWhenFaceDown": false,
      "Hands": false,
      "CustomMesh": {
        "MeshURL": "https://steamusercontent-a.akamaihd.net/ugc/1761463413139116026/6C80E8EBD28F1C7E8E816024BD7512FFDF676E13/",
        "DiffuseURL": "",
        "NormalURL": "",
        "ColliderURL": "",
        "Convex": true,
        "MaterialIndex": 0,
        "TypeIndex": 1,
        "CustomShader": {
          "SpecularColor": {
            "r": 1.0,
            "g": 1.0,
            "b": 1.0
          },
          "SpecularIntensity": 0.0,
          "SpecularSharpness": 7.0,
          "FresnelStrength": 0.4
        },
        "CastShadows": true
      },
      "LuaScript": "",
      "LuaScriptState": "",
      "XmlUI": "",
      "AttachedSnapPoints": [
        {
          "Position": {
            "x": 0.0004,
            "y": 2.59,
            "z": -0.0001
          }
        }
      ]
    },
    "4": {
      "GUID": "3df445",
      "Name": "Custom_Model",
      "Transform": {
        "posX": -21.8798,
        "posY": 0.96,
        "posZ": -1.3474,
        "rotX": 0.0,
        "rotY": 179.9978,
        "rotZ": 0.0,
        "scaleX": 1.0,
        "scaleY": 1.0,
        "scaleZ": 1.0
      },
      "Nickname": "City",
      "Description": "",
      "GMNotes": "",
      "AltLookAngle": {
        "x": 0.0,
        "y": 0.0,
        "z": 0.0
      },
      "ColorDiffuse": {
        "r": 0.8721,
        "g": 0.8721,
        "b": 0.8721
      },
      "Tags": [
        "City",
        "Highlight"
      ],
      "LayoutGroupSortIndex": 0,
      "Value": 0,
      "Locked": false,
      "Grid": false,
      "Snap": true,
      "IgnoreFoW": false,
      "MeasureMovement": false,
      "DragSelectable": true,
      "Autoraise": true,
      "Sticky": true,
      "Tooltip": true,
      "GridProjection": false,
      "HideWhenFaceDown": false,
      "Hands": false,
      "CustomMesh": {
        "MeshURL": "https://steamusercontent-a.akamaihd.net/ugc/1761463413139116026/6C80E8EBD28F1C7E8E816024BD7512FFDF676E13/",
        "DiffuseURL": "",
        "NormalURL": "",
        "ColliderURL": "",
        "Convex": true,
        "MaterialIndex": 0,
        "TypeIndex": 1,
        "CustomShader": {
          "SpecularColor": {
            "r": 1.0,
            "g": 1.0,
            "b": 1.0
          },
          "SpecularIntensity": 0.0,
          "SpecularSharpness": 7.0,
          "FresnelStrength": 0.4
        },
        "CastShadows": true
      },
      "LuaScript": "",
      "LuaScriptState": "",
      "XmlUI": "",
      "AttachedSnapPoints": [
        {
          "Position": {
            "x": 0.0004,
            "y": 2.59,
            "z": -0.0001
          }
        }
      ]
    },
    "5": {
      "GUID": "fe4a39",
      "Name": "Custom_Model",
      "Transform": {
        "posX": -19.7464,
        "posY": 0.96,
        "posZ": -1.3297,
        "rotX": 0.0,
        "rotY": 179.9978,
        "rotZ": 0.0,
        "scaleX": 1.0,
        "scaleY": 1.0,
        "scaleZ": 1.0
      },
      "Nickname": "City",
      "Description": "",
      "GMNotes": "",
      "AltLookAngle": {
        "x": 0.0,
        "y": 0.0,
        "z": 0.0
      },
      "ColorDiffuse": {
        "r": 0.8721,
        "g": 0.8721,
        "b": 0.8721
      },
      "Tags": [
        "City",
        "Highlight"
      ],
      "LayoutGroupSortIndex": 0,
      "Value": 0,
      "Locked": false,
      "Grid": false,
      "Snap": true,
      "IgnoreFoW": false,
      "MeasureMovement": false,
      "DragSelectable": true,
      "Autoraise": true,
      "Sticky": true,
      "Tooltip": true,
      "GridProjection": false,
      "HideWhenFaceDown": false,
      "Hands": false,
      "CustomMesh": {
        "MeshURL": "https://steamusercontent-a.akamaihd.net/ugc/1761463413139116026/6C80E8EBD28F1C7E8E816024BD7512FFDF676E13/",
        "DiffuseURL": "",
        "NormalURL": "",
        "ColliderURL": "",
        "Convex": true,
        "MaterialIndex": 0,
        "TypeIndex": 1,
        "CustomShader": {
          "SpecularColor": {
            "r": 1.0,
            "g": 1.0,
            "b": 1.0
          },
          "SpecularIntensity": 0.0,
          "SpecularSharpness": 7.0,
          "FresnelStrength": 0.4
        },
        "CastShadows": true
      },
      "LuaScript": "",
      "LuaScriptState": "",
      "XmlUI": "",
      "AttachedSnapPoints": [
        {
          "Position": {
            "x": 0.0004,
            "y": 2.59,
            "z": -0.0001
          }
        }
      ]
    },
    "6": {
      "GUID": "bddd3e",
      "Name": "Custom_Model",
      "Transform": {
        "posX": -17.6508,
        "posY": 0.96,
        "posZ": -1.4287,
        "rotX": 0.0,
        "rotY": 179.9978,
        "rotZ": 0.0,
        "scaleX": 1.0,
        "scaleY": 1.0,
        "scaleZ": 1.0
      },
      "Nickname": "City",
      "Description": "",
      "GMNotes": "",
      "AltLookAngle": {
        "x": 0.0,
        "y": 0.0,
        "z": 0.0
      },
      "ColorDiffuse": {
        "r": 0.8721,
        "g": 0.8721,
        "b": 0.8721
      },
      "Tags": [
        "City",
        "Highlight"
      ],
      "LayoutGroupSortIndex": 0,
      "Value": 0,
      "Locked": false,
      "Grid": false,
      "Snap": true,
      "IgnoreFoW": false,
      "MeasureMovement": false,
      "DragSelectable": true,
      "Autoraise": true,
      "Sticky": true,
      "Tooltip": true,
      "GridProjection": false,
      "HideWhenFaceDown": false,
      "Hands": false,
      "CustomMesh": {
        "MeshURL": "https://steamusercontent-a.akamaihd.net/ugc/1761463413139116026/6C80E8EBD28F1C7E8E816024BD7512FFDF676E13/",
        "DiffuseURL": "",
        "NormalURL": "",
        "ColliderURL": "",
        "Convex": true,
        "MaterialIndex": 0,
        "TypeIndex": 1,
        "CustomShader": {
          "SpecularColor": {
            "r": 1.0,
            "g": 1.0,
            "b": 1.0
          },
          "SpecularIntensity": 0.0,
          "SpecularSharpness": 7.0,
          "FresnelStrength": 0.4
        },
        "CastShadows": true
      },
      "LuaScript": "",
      "LuaScriptState": "",
      "XmlUI": "",
      "AttachedSnapPoints": [
        {
          "Position": {
            "x": 0.0004,
            "y": 2.59,
            "z": -0.0001
          }
        }
      ]
    },
    "7": {
      "GUID": "03d89f",
      "Name": "Custom_Model",
      "Transform": {
        "posX": -15.6726,
        "posY": 0.96,
        "posZ": -1.4123,
        "rotX": 0.0,
        "rotY": 179.9978,
        "rotZ": 0.0,
        "scaleX": 1.0,
        "scaleY": 1.0,
        "scaleZ": 1.0
      },
      "Nickname": "City",
      "Description": "",
      "GMNotes": "",
      "AltLookAngle": {
        "x": 0.0,
        "y": 0.0,
        "z": 0.0
      },
      "ColorDiffuse": {
        "r": 0.8721,
        "g": 0.8721,
        "b": 0.8721
      },
      "Tags": [
        "City",
        "Highlight"
      ],
      "LayoutGroupSortIndex": 0,
      "Value": 0,
      "Locked": false,
      "Grid": false,
      "Snap": true,
      "IgnoreFoW": false,
      "MeasureMovement": false,
      "DragSelectable": true,
      "Autoraise": true,
      "Sticky": true,
      "Tooltip": true,
      "GridProjection": false,
      "HideWhenFaceDown": false,
      "Hands": false,
      "CustomMesh": {
        "MeshURL": "https://steamusercontent-a.akamaihd.net/ugc/1761463413139116026/6C80E8EBD28F1C7E8E816024BD7512FFDF676E13/",
        "DiffuseURL": "",
        "NormalURL": "",
        "ColliderURL": "",
        "Convex": true,
        "MaterialIndex": 0,
        "TypeIndex": 1,
        "CustomShader": {
          "SpecularColor": {
            "r": 1.0,
            "g": 1.0,
            "b": 1.0
          },
          "SpecularIntensity": 0.0,
          "SpecularSharpness": 7.0,
          "FresnelStrength": 0.4
        },
        "CastShadows": true
      },
      "LuaScript": "",
      "LuaScriptState": "",
      "XmlUI": "",
      "AttachedSnapPoints": [
        {
          "Position": {
            "x": 0.0004,
            "y": 2.59,
            "z": -0.0001
          }
        }
      ]
    },
    "8": {
      "GUID": "4d8443",
      "Name": "Custom_Model",
      "Transform": {
        "posX": -13.6559,
        "posY": 0.96,
        "posZ": -1.3567,
        "rotX": 0.0,
        "rotY": 179.9978,
        "rotZ": 0.0,
        "scaleX": 1.0,
        "scaleY": 1.0,
        "scaleZ": 1.0
      },
      "Nickname": "City",
      "Description": "",
      "GMNotes": "",
      "AltLookAngle": {
        "x": 0.0,
        "y": 0.0,
        "z": 0.0
      },
      "ColorDiffuse": {
        "r": 0.8721,
        "g": 0.8721,
        "b": 0.8721
      },
      "Tags": [
        "City",
        "Highlight"
      ],
      "LayoutGroupSortIndex": 0,
      "Value": 0,
      "Locked": false,
      "Grid": false,
      "Snap": true,
      "IgnoreFoW": false,
      "MeasureMovement": false,
      "DragSelectable": true,
      "Autoraise": true,
      "Sticky": true,
      "Tooltip": true,
      "GridProjection": false,
      "HideWhenFaceDown": false,
      "Hands": false,
      "CustomMesh": {
        "MeshURL": "https://steamusercontent-a.akamaihd.net/ugc/1761463413139116026/6C80E8EBD28F1C7E8E816024BD7512FFDF676E13/",
        "DiffuseURL": "",
        "NormalURL": "",
        "ColliderURL": "",
        "Convex": true,
        "MaterialIndex": 0,
        "TypeIndex": 1,
        "CustomShader": {
          "SpecularColor": {
            "r": 1.0,
            "g": 1.0,
            "b": 1.0
          },
          "SpecularIntensity": 0.0,
          "SpecularSharpness": 7.0,
          "FresnelStrength": 0.4
        },
        "CastShadows": true
      },
      "LuaScript": "",
      "LuaScriptState": "",
      "XmlUI": "",
      "AttachedSnapPoints": [
        {
          "Position": {
            "x": 0.0004,
            "y": 2.59,
            "z": -0.0001
          }
        }
      ]
    },
    "9": {
      "GUID": "96c5d3",
      "Name": "Custom_Model",
      "Transform": {
        "posX": -11.7553,
        "posY": 0.96,
        "posZ": -1.341,
        "rotX": 0.0,
        "rotY": 179.9978,
        "rotZ": 0.0,
        "scaleX": 1.0,
        "scaleY": 1.0,
        "scaleZ": 1.0
      },
      "Nickname": "City",
      "Description": "",
      "GMNotes": "",
      "AltLookAngle": {
        "x": 0.0,
        "y": 0.0,
        "z": 0.0
      },
      "ColorDiffuse": {
        "r": 0.8721,
        "g": 0.8721,
        "b": 0.8721
      },
      "Tags": [
        "City",
        "Highlight"
      ],
      "LayoutGroupSortIndex": 0,
      "Value": 0,
      "Locked": false,
      "Grid": false,
      "Snap": true,
      "IgnoreFoW": false,
      "MeasureMovement": false,
      "DragSelectable": true,
      "Autoraise": true,
      "Sticky": true,
      "Tooltip": true,
      "GridProjection": false,
      "HideWhenFaceDown": false,
      "Hands": false,
      "CustomMesh": {
        "MeshURL": "https://steamusercontent-a.akamaihd.net/ugc/1761463413139116026/6C80E8EBD28F1C7E8E816024BD7512FFDF676E13/",
        "DiffuseURL": "",
        "NormalURL": "",
        "ColliderURL": "",
        "Convex": true,
        "MaterialIndex": 0,
        "TypeIndex": 1,
        "CustomShader": {
          "SpecularColor": {
            "r": 1.0,
            "g": 1.0,
            "b": 1.0
          },
          "SpecularIntensity": 0.0,
          "SpecularSharpness": 7.0,
          "FresnelStrength": 0.4
        },
        "CastShadows": true
      },
      "LuaScript": "",
      "LuaScriptState": "",
      "XmlUI": "",
      "AttachedSnapPoints": [
        {
          "Position": {
            "x": 0.0004,
            "y": 2.59,
            "z": -0.0001
          }
        }
      ]
    },
    "10": {
      "GUID": "81d6ed",
      "Name": "Custom_Model",
      "Transform": {
        "posX": -10.0867,
        "posY": 0.96,
        "posZ": -1.4047,
        "rotX": 0.0,
        "rotY": 179.9978,
        "rotZ": 0.0,
        "scaleX": 1.0,
        "scaleY": 1.0,
        "scaleZ": 1.0
      },
      "Nickname": "City",
      "Description": "",
      "GMNotes": "",
      "AltLookAngle": {
        "x": 0.0,
        "y": 0.0,
        "z": 0.0
      },
      "ColorDiffuse": {
        "r": 0.8721,
        "g": 0.8721,
        "b": 0.8721
      },
      "Tags": [
        "City",
        "Highlight"
      ],
      "LayoutGroupSortIndex": 0,
      "Value": 0,
      "Locked": false,
      "Grid": false,
      "Snap": true,
      "IgnoreFoW": false,
      "MeasureMovement": false,
      "DragSelectable": true,
      "Autoraise": true,
      "Sticky": true,
      "Tooltip": true,
      "GridProjection": false,
      "HideWhenFaceDown": false,
      "Hands": false,
      "CustomMesh": {
        "MeshURL": "https://steamusercontent-a.akamaihd.net/ugc/1761463413139116026/6C80E8EBD28F1C7E8E816024BD7512FFDF676E13/",
        "DiffuseURL": "",
        "NormalURL": "",
        "ColliderURL": "",
        "Convex": true,
        "MaterialIndex": 0,
        "TypeIndex": 1,
        "CustomShader": {
          "SpecularColor": {
            "r": 1.0,
            "g": 1.0,
            "b": 1.0
          },
          "SpecularIntensity": 0.0,
          "SpecularSharpness": 7.0,
          "FresnelStrength": 0.4
        },
        "CastShadows": true
      },
      "LuaScript": "",
      "LuaScriptState": "",
      "XmlUI": "",
      "AttachedSnapPoints": [
        {
          "Position": {
            "x": 0.0004,
            "y": 2.59,
            "z": -0.0001
          }
        }
      ]
    }
  }
}
