{
  "Name": "Custom_Model",
  "Transform": {
    "posX": 116.4322,
    "posY": 1.0295,
    "posZ": 54.1118,
    "rotX": 0.0,
    "rotY": 359.9817,
    "rotZ": 0.0,
    "scaleX": 0.475,
    "scaleY": 0.475,
    "scaleZ": 0.475
  },
  "Nickname": "1 Energy",
  "Description": "Pays for Power Cards. Carries over from turn to turn.",
  "GMNotes": "",
  "ColorDiffuse": {
    "r": 1.0,
    "g": 1.0,
    "b": 1.0
  },
  "Tags": [
    "Destroy"
  ],
  "LayoutGroupSortIndex": 0,
  "Value": 0,
  "Locked": false,
  "Grid": false,
  "Snap": true,
  "IgnoreFoW": false,
  "MeasureMovement": false,
  "DragSelectable": true,
  "Autoraise": true,
  "Sticky": false,
  "Tooltip": true,
  "GridProjection": false,
  "HideWhenFaceDown": false,
  "Hands": false,
  "CustomMesh": {
    "MeshURL": "http://cloud-3.steamusercontent.com/ugc/1749061746121830431/DE000E849E99F439C3775E5C92E327CE09E4DB65/",
    "DiffuseURL": "http://cloud-3.steamusercontent.com/ugc/1753560381472358304/A200B815400F7CF50C47E4EBE30AA806B52787A7/",
    "NormalURL": "",
    "ColliderURL": "",
    "Convex": true,
    "MaterialIndex": 1,
    "TypeIndex": 5,
    "CastShadows": true
  }
}
