{
  "Name": "go_game_piece_white",
  "Transform": {
    "posX": -41.8165474,
    "posY": 1.782514,
    "posZ": 47.3825569,
    "rotX": 352.2939,
    "rotY": 352.486481,
    "rotZ": 36.1546021,
    "scaleX": 1.19999993,
    "scaleY": 1.19999993,
    "scaleZ": 1.19999993
  },
  "Nickname": "Yellow's Presence",
  "Description": "",
  "GMNotes": "",
  "ColorDiffuse": {
    "r": 0.7849399,
    "g": 0.7791328,
    "b": 0.241952538
  },
  "Locked": false,
  "Grid": false,
  "Snap": true,
  "IgnoreFoW": false,
  "MeasureMovement": false,
  "DragSelectable": true,
  "Autoraise": true,
  "Sticky": false,
  "Tooltip": true,
  "GridProjection": false,
  "HideWhenFaceDown": false,
  "Hands": false,
  "LuaScriptState": "",
  "XmlUI": ""
}
